snsql/__init__.py
snsql/_ast/__init__.py
snsql/_ast/ast.py
snsql/_ast/expression.py
snsql/_ast/expressions/__init__.py
snsql/_ast/expressions/date.py
snsql/_ast/expressions/logical.py
snsql/_ast/expressions/numeric.py
snsql/_ast/expressions/sql.py
snsql/_ast/expressions/string.py
snsql/_ast/expressions/types.py
snsql/_ast/tokens.py
snsql/_ast/validate.py
snsql/connect.py
snsql/metadata.py
snsql/reader/__init__.py
snsql/reader/base.py
snsql/sql/__init__.py
snsql/sql/_mechanisms/__init__.py
snsql/sql/_mechanisms/approx_bounds.py
snsql/sql/_mechanisms/base.py
snsql/sql/_mechanisms/gaussian.py
snsql/sql/_mechanisms/laplace.py
snsql/sql/_mechanisms/normal.py
snsql/sql/_mechanisms/rand.py
snsql/sql/dpsu.py
snsql/sql/odometer.py
snsql/sql/parse.py
snsql/sql/parser/.gitignore
snsql/sql/parser/Makefile
snsql/sql/parser/README.md
snsql/sql/parser/SqlSmall.g4
snsql/sql/parser/SqlSmallErrorListener.py
snsql/sql/parser/SqlSmallLexer.py
snsql/sql/parser/SqlSmallParser.py
snsql/sql/parser/SqlSmallVisitor.py
snsql/sql/parser/__init__.py
snsql/sql/privacy.py
snsql/sql/private_reader.py
snsql/sql/private_rewriter.py
snsql/sql/reader/__init__.py
snsql/sql/reader/base.py
snsql/sql/reader/bigquery.py
snsql/sql/reader/engine.py
snsql/sql/reader/mysql.py
snsql/sql/reader/pandas.py
snsql/sql/reader/postgres.py
snsql/sql/reader/presto.py
snsql/sql/reader/probe.py
snsql/sql/reader/spark.py
snsql/sql/reader/sql_server.py
snsql/sql/reader/sqlite.py
snsql/xpath/__init__.py
snsql/xpath/ast.py
snsql/xpath/parse.py
snsql/xpath/parser/.gitignore
snsql/xpath/parser/Makefile
snsql/xpath/parser/XPath.g4
snsql/xpath/parser/XPathErrorListener.py
snsql/xpath/parser/XPathLexer.py
snsql/xpath/parser/XPathParser.py
snsql/xpath/parser/XPathVisitor.py
snsql/xpath/parser/__init__.py
smartnoise_sql-1.0.6.dist-info/METADATA
smartnoise_sql-1.0.6.dist-info/WHEEL
smartnoise_sql-1.0.6.dist-info/RECORD
