Metadata-Version: 2.3
Name: smartnoise-sql
Version: 1.0.6
Summary: Differentially Private SQL Queries
License: MIT
Author: SmartNoise Team
Author-email: smartnoise@opendp.org
Requires-Python: >=3.8,<3.14
Classifier: License :: OSI Approved :: MIT License
Classifier: Programming Language :: Python :: 3
Classifier: Programming Language :: Python :: 3.8
Classifier: Programming Language :: Python :: 3.9
Classifier: Programming Language :: Python :: 3.10
Classifier: Programming Language :: Python :: 3.11
Classifier: Programming Language :: Python :: 3.12
Classifier: Programming Language :: Python :: 3.13
Requires-Dist: PyYAML (>=6.0.1,<7.0.0)
Requires-Dist: antlr4-python3-runtime (==4.9.3)
Requires-Dist: graphviz (>=0.17,<1.0)
Requires-Dist: opendp (>=0.8.0,<0.13.0)
Requires-Dist: pandas (>=2.0.1,<3.0.0)
Requires-Dist: sqlalchemy (>=2.0.0,<3.0.0)
Project-URL: Homepage, https://smartnoise.org
Project-URL: Repository, https://github.com/opendp/smartnoise-sdk
